MANIFEST.in
README.rst
setup.cfg
setup.py
searchandreco/__init__.py
searchandreco/index.py
searchandreco/originals_index.py
searchandreco/paginationspellcheck.py
searchandreco/sportscrumbs_index.py
searchandreco/urls.py
searchandreco.egg-info/PKG-INFO
searchandreco.egg-info/SOURCES.txt
searchandreco.egg-info/dependency_links.txt
searchandreco.egg-info/requires.txt
searchandreco.egg-info/top_level.txt
searchandreco/eswrapper/__init__.py
searchandreco/eswrapper/defines.py
searchandreco/eswrapper/eswrapper.py
searchandreco/eswrapper/originals_defines.py
searchandreco/eswrapper/originals_eswrapper.py
searchandreco/eswrapper/settings.py
searchandreco/eswrapper/sportscrumbs_defines.py
searchandreco/eswrapper/sportscrumbs_eswrapper.py
searchandreco/eswrapper/utils.py
searchandreco/exceptions/__init__.py
searchandreco/exceptions/loggerfileload.py
searchandreco/tests/__init__.py
searchandreco/tests/base.py
searchandreco/tests/test_gazabpost.py
searchandreco/tests/test_originals.py
searchandreco/tests/test_scoopwhoop.py
searchandreco/tests/test_vagabomb.py
searchandreco/tests/test_zcleardb.py