Metadata-Version: 1.1
Name: searchandreco
Version: 1.25.dev1
Summary: All Search
Home-page: UNKNOWN
Author: Chitraangi Sharma
Author-email: chitraangi@scoopwhoop.com
License: MIT
Keywords: all search
Platform: UNKNOWN
Classifier: Development Status :: 3 - Alpha
Classifier: Intended Audience :: Developers
Classifier: Topic :: Software Development :: Build Tools
Classifier: License :: OSI Approved :: MIT License
Classifier: Programming Language :: Python :: 2.7
